wproxy/__init__.py
wproxy/__main__.py
wproxy/runner.py
wproxy/wproxy.py
wproxy-0.0.2.dist-info/METADATA
wproxy-0.0.2.dist-info/WHEEL
wproxy-0.0.2.dist-info/entry_points.txt
wproxy-0.0.2.dist-info/top_level.txt
wproxy-0.0.2.dist-info/RECORD
