Metadata-Version: 2.1
Name: wproxy
Version: 0.0.2
Summary: Websocket proxy
Author-email: Ferdinand Silva <ferdinandsilva@ferdinandsilva.com>
Project-URL: Home, https://github.com/six519/wproxy
Classifier: Intended Audience :: Developers
Classifier: Natural Language :: English
Classifier: Programming Language :: Python
Classifier: Programming Language :: Python :: 3
Classifier: Topic :: Software Development :: Libraries :: Python Modules
Requires-Python: >=3.6
Requires-Dist: websockets
